django_tenant_schemas_q/__init__.py
django_tenant_schemas_q/cluster.py
django_tenant_schemas_q/custom.py
django_tenant_schemas_q/utils.py
django_tenant_schemas_q/management/__init.py
django_tenant_schemas_q/management/commands/__init__.py
django_tenant_schemas_q/management/commands/mscluster.py
django_tenant_schemas_q-1.0.1.dist-info/LICENSE
django_tenant_schemas_q-1.0.1.dist-info/METADATA
django_tenant_schemas_q-1.0.1.dist-info/WHEEL
django_tenant_schemas_q-1.0.1.dist-info/top_level.txt
django_tenant_schemas_q-1.0.1.dist-info/RECORD
