Metadata-Version: 2.1
Name: django-tenant-schemas-q
Version: 1.0.1
Summary: An integration package for Django-Q with Django Tenant Schemas
Home-page: https://github.com/rajeshyogeshwar/django-tenant-schemas-q
Author: Rajesh Yogeshwar
Author-email: rajesh.yogeshwar@gmail.com
License: MIT
Platform: UNKNOWN
Classifier: Programming Language :: Python :: 3
Classifier: License :: OSI Approved :: MIT License
Classifier: Operating System :: OS Independent
Requires-Python: >=3.7
Requires-Dist: croniter (==0.3.36)
Requires-Dist: django-q (>=1.2.1)
Requires-Dist: django-tenant-schemas (>=1.10.0)
